Metadata-Version: 1.0
Name: distributionshajimete
Version: 1.0
Summary: Gaussian distributions
Home-page: UNKNOWN
Author: Miki Kaneko
Author-email: novmikicity@gmail.com
License: UNKNOWN
Platform: UNKNOWN
